Workbook

Sheet Dashboard
A1: AbridMoroccoTrip — Booking Management Dashboard
C4: Total Bookings | E4: Total Revenue ($) | G4: Pending Inquiries | I4: Confirmed Trips
C5: =COUNTA('Bookings'!A5:A100) | E5: =SUM('Bookings'!I5:I100) | G5: =COUNTIF('Bookings'!K5:K100, "Pending") | I5: =COUNTIF('Bookings'!K5:K100, "Confirmed")
B8: Tour Performance Summary
B9: Tour Package | C9: Base Price | D9: Bookings Count | E9: Total Revenue
B10: Marrakech Discovery Tour | C10: 55 | D10: =COUNTIF(Bookings!E$5:E$100, B10) | E10: =SUMIF(Bookings!E$5:E$100, B10, Bookings!I$5:I$100)
B11: Atlas Mountains & Ourika Valley | C11: 125 | D11: =COUNTIF(Bookings!E$5:E$100, B11) | E11: =SUMIF(Bookings!E$5:E$100, B11, Bookings!I$5:I$100)
B12: Essaouira Coastal Escape | C12: 95 | D12: =COUNTIF(Bookings!E$5:E$100, B12) | E12: =SUMIF(Bookings!E$5:E$100, B12, Bookings!I$5:I$100)
B13: Merzouga Desert Adventure (3D/2N) | C13: 145 | D13: =COUNTIF(Bookings!E$5:E$100, B13) | E13: =SUMIF(Bookings!E$5:E$100, B13, Bookings!I$5:I$100)
B14: Imperial Cities Circuit (8D/7N) | C14: 2950 | D14: =COUNTIF(Bookings!E$5:E$100, B14) | E14: =SUMIF(Bookings!E$5:E$100, B14, Bookings!I$5:I$100)
B15: Sunrise Balloon over Marrakech | C15: 260 | D15: =COUNTIF(Bookings!E$5:E$100, B15) | E15: =SUMIF(Bookings!E$5:E$100, B15, Bookings!I$5:I$100)
B16: Private Tailor-Made Trip | C16: 1500 | D16: =COUNTIF(Bookings!E$5:E$100, B16) | E16: =SUMIF(Bookings!E$5:E$100, B16, Bookings!I$5:I$100)

Sheet Bookings
A1: AbridMoroccoTrip — Master Booking Register
A4: Booking ID | B4: Date Received | C4: Customer Name | D4: Contact (Phone/Email) | E4: Interested Tour | F4: Travel Date | G4: Travelers | H4: Price / Person ($) | I4: Total Price ($) | J4: Payment Status | K4: Booking Status | L4: Assigned Guide | M4: Special Requests & Notes
A5: AMT-2026-001 | B5: 2026-07-20 | C5: Jean Dupont | D5: +33 6 12 34 56 78 | jean@example.fr | E5: Merzouga Desert Adventure (3D/2N) | F5: 2026-08-10 | G5: 2 | H5: 145 | I5: =G5*H5 | J5: Paid | K5: Confirmed | L5: Abdellah | M5: Vegetarian meals requested
A6: AMT-2026-002 | B6: 2026-07-21 | C6: Sarah Jenkins | D6: +44 7700 900077 | sarah.j@example.co.uk | E6: Marrakech Discovery Tour | F6: 2026-08-02 | G6: 4 | H6: 55 | I6: =G6*H6 | J6: Unpaid (Cash) | K6: Confirmed | L6: Abdellah | M6: Hotel pickup at Riad Alma
A7: AMT-2026-003 | B7: 2026-07-22 | C7: Marco Müller | D7: +49 151 23456789 | marco@example.de | E7: Atlas Mountains & Ourika Valley | F7: 2026-08-05 | G7: 2 | H7: 125 | I7: =G7*H7 | J7: Deposit Paid | K7: Confirmed | L7: Hassan | M7: Private 4x4 needed
A8: AMT-2026-004 | B8: 2026-07-24 | C8: Maria Garcia | D8: +34 612 345 678 | maria@example.es | E8: Essaouira Coastal Escape | F8: 2026-08-12 | G8: 3 | H8: 95 | I8: =G8*H8 | J8: Unpaid (Cash) | K8: Pending | L8: Abdellah | M8: Prefers Spanish speaking guide
A9: AMT-2026-005 | B9: 2026-07-25 | C9: John Smith | D9: +1 212 555 0199 | john.smith@example.com | E9: Imperial Cities Circuit (8D/7N) | F9: 2026-09-01 | G9: 2 | H9: 2950 | I9: =G9*H9 | J9: Deposit Paid | K9: Confirmed | L9: Youssef | M9: Luxury riads preferred
A10: AMT-2026-006 | B10: 2026-07-26 | C10: Lisa Ray | D10: +1 312 555 0144 | lisa@example.com | E10: Sunrise Balloon over Marrakech | F10: 2026-08-03 | G10: 2 | H10: 260 | I10: =G10*H10 | J10: Paid | K10: Confirmed | L10: Flight Partner | M10: Honeymoon couple - special touch
A11: AMT-2026-007 | B11: 2026-07-27 | C11: Emma Watson | D11: +1 416 555 0188 | emma@example.ca | E11: Private Tailor-Made Trip | F11: 2026-09-15 | G11: 5 | H11: 1200 | I11: =G11*H11 | J11: Inquired | K11: Pending | L11: Abdellah | M11: Custom 10-day luxury itinerary requested
